blipy/__init__.py
blipy/arquivo_csv.py
blipy/arquivo_posicional.py
blipy/conexao_bd.py
blipy/enum_tipo_col_bd.py
blipy/erro.py
blipy/func_transformacao.py
blipy/job.py
blipy/jsonstring.py
blipy/planilha.py
blipy/profiling.py
blipy/tabela_dataframe.py
blipy/tabela_entrada.py
blipy/tabela_html.py
blipy/tabela_saida.py
blipy/utils.py
stnblipy-8.0.0.dist-info/METADATA
stnblipy-8.0.0.dist-info/WHEEL
stnblipy-8.0.0.dist-info/top_level.txt
stnblipy-8.0.0.dist-info/RECORD
