Metadata-Version: 2.4
Name: stnblipy
Version: 8.0.0
Summary: Framework para rotinas de ETL
Author: Secretaria do Tesouro Nacional
License: GPL v2
Keywords: python,ETL,framework
Classifier: Programming Language :: Python :: 3.13
Requires-Dist: beautifulsoup4==4.13.4
Requires-Dist: bs4==0.0.2
Requires-Dist: cffi==1.17.1
Requires-Dist: cryptography==45.0.5
Requires-Dist: et_xmlfile==2.0.0
Requires-Dist: greenlet==3.2.3
Requires-Dist: html5lib==1.1
Requires-Dist: JayDeBeApi==1.2.3
Requires-Dist: jpype1==1.5.2
Requires-Dist: lxml==6.0.0
Requires-Dist: multipledispatch==1.0.0
Requires-Dist: numpy==2.3.2
Requires-Dist: openpyxl==3.1.5
Requires-Dist: oracledb==3.2.0
Requires-Dist: packaging==25.0
Requires-Dist: pandas==2.3.1
Requires-Dist: pycparser==2.22
Requires-Dist: python-dateutil==2.9.0.post0
Requires-Dist: pytz==2025.2
Requires-Dist: six==1.17.0
Requires-Dist: soupsieve==2.7
Requires-Dist: SQLAlchemy==2.0.41
Requires-Dist: typing_extensions==4.14.1
Requires-Dist: tzdata==2025.2
Requires-Dist: webencodings==0.5.1
Requires-Dist: wget==3.2
Requires-Dist: xlrd==2.0.2
Dynamic: author
Dynamic: classifier
Dynamic: description
Dynamic: keywords
Dynamic: license
Dynamic: requires-dist
Dynamic: summary
